aiorecaptcha/__init__.py
aio_recaptcha-0.1.0.dist-info/LICENSE
aio_recaptcha-0.1.0.dist-info/METADATA
aio_recaptcha-0.1.0.dist-info/WHEEL
aio_recaptcha-0.1.0.dist-info/top_level.txt
aio_recaptcha-0.1.0.dist-info/RECORD
