Metadata-Version: 2.1
Name: aio-recaptcha
Version: 0.1.0
Summary: Recaptcha v2 and v3
Home-page: https://github.com/omarryhan/aio-recaptcha
Author: Omar Ryhan
Author-email: omarryhan@gmail.com
License: MIT
Platform: UNKNOWN
Classifier: Programming Language :: Python :: 3
Classifier: Operating System :: OS Independent
Requires-Dist: aiohttp
